kgrid_python_runtime/VERSION
kgrid_python_runtime/__init__.py
kgrid_python_runtime/__main__.py
kgrid_python_runtime/app.py
kgrid_python_runtime/context.py
kgrid_python_runtime/exceptions.py
kgrid_python_runtime-0.1.0.dist-info/LICENSE
kgrid_python_runtime-0.1.0.dist-info/METADATA
kgrid_python_runtime-0.1.0.dist-info/WHEEL
kgrid_python_runtime-0.1.0.dist-info/top_level.txt
kgrid_python_runtime-0.1.0.dist-info/RECORD
