Metadata-Version: 2.1
Name: kgrid-python-runtime
Version: 0.1.0
Summary: A runtime for python-based Knowledge Objects
Home-page: https://github.com/kgrid/kgrid-python-runtime
Author: Kgrid Developers
Author-email: kgrid-developers@umich.edu
License: UNKNOWN
Platform: UNKNOWN
Classifier: Programming Language :: Python :: 3
Classifier: License :: OSI Approved :: GNU General Public License v3 (GPLv3)
Classifier: Operating System :: OS Independent
Classifier: Framework :: Flask
Classifier: Natural Language :: English
Classifier: Topic :: Scientific/Engineering :: Medical Science Apps.
Requires-Python: >=3.8
Requires-Dist: flask (==1.1.2)
Requires-Dist: Flask-Script (==2.0.6)
Requires-Dist: requests (==2.25.1)
Requires-Dist: werkzeug (==1.0.1)
Requires-Dist: responses (==0.13.2)
Requires-Dist: setuptools (~=56.0.0)
